Workbook

Sheet Presupuesto
A1: Presupuesto
A2: Mes | B2: Seguro | C2: Patente | D2: Contenedores | E2: Jardin | F2: Niñera | G2: SIET | H2: Internet | I2: Luz | J2: Gastos terreno | K2: Tarjeta CDE | L2: Tarjeta ITAU | M2: Tarjeta recompensa | N2: Amandaye | O2: Nafta y peaje | P2: Corte pasto | Q2: Perros | R2: Comida | S2: Limpieza | T2: paseo | U2: Servicio camioneta | V2: Ablandador | W2: Jardineria | X2: Banco y seguros | Y2: Regalos | Z2: Gas y calefacción | AA2: Extra | AB2: Cumple Roci | AC2: suma gastos | AD2: C/U | AE2: Fondo | AF2: Ahorro | AG2: Sueldo | AH2: Deposita Sofi | AI2: Deposita Nico | AJ2: Banco compartido
A3: Mayo | D3: 15500 | E3: 10600 | F3: 26100 | G3: 1000 | H3: 3500 | I3: 3000 | J3: 1000 | K3: 0 | L3: 18100 | M3: 22200 | N3: 850 | O3: 10000 | P3: 1800 | Q3: 2500 | R3: 20000 | S3: 2500 | T3: 5000 | U3: 15000 | W3: 3000 | X3: 1500 | Y3: 2000 | Z3: 500 | AA3: 5000 | AC3: =SUM(B3:AB3) -> 170650 | AD3: =+AB3/2 -> 0 | AE3: 10000 | AF3: =AG3-AD3-AE3 -> 85000 | AG3: 95000 | AH3: =AC3/2-M3 -> 63125 | AI3: =AC3/2-D3 -> 69825 | AJ3: =AH3+AI3 -> 132950
A4: Junio | D4: 15550 | E4: 10600 | F4: 35500 | G4: 1000 | H4: 3500 | I4: 3000 | J4: 1000 | K4: 1300 | L4: 10000 | M4: 8000 | N4: 850 | O4: 11000 | P4: 1800 | Q4: 2500 | R4: 20000 | S4: 2500 | T4: 5000 | W4: 3000 | X4: 1500 | Y4: 2000 | Z4: =1350+2500 -> 3850 | AA4: 5000 | AB4: 18000 | AC4: =SUM(B4:AB4) -> 166450 | AD4: =+AB4/2 -> 9000 | AE4: 10000 | AF4: =AG4-AD4-AE4 -> 76000 | AG4: 95000 | AH4: =AC4/2-M4 -> 75225 | AI4: =AC4/2-D4 -> 67675 | AJ4: =AH4+AI4 -> 142900
A5: Julio | C5: 4369 | D5: 15600 | E5: 0 | F5: 26100 | G5: 1000 | H5: 3500 | I5: 3000 | J5: 1000 | K5: =1300+9800+6600 -> 17700 | L5: 7500 | M5: 7500 | N5: 850 | O5: 4400 | P5: 1800 | Q5: 2500 | R5: 20000 | S5: 2500 | T5: 5000 | V5: 1500 | W5: 3000 | X5: 1500 | Y5: 2000 | AA5: 5000 | AC5: =SUM(B5:AB5) -> 137319 | AD5: =+AB5/2 -> 0 | AE5: 10000 | AF5: =AG5-AD5-AE5 -> 85000 | AG5: 95000 | AH5: =AC5/2-M5 -> 61159.5 | AI5: =AC5/2-D5 -> 53059.5 | AJ5: =AH5+AI5 -> 114219
A6: Agosto | D6: 15691 | E6: 0 | F6: 28611 | G6: 1185 | H6: 3291.56 | I6: 3335.41 | J6: 700 | K6: 18000 | L6: 14000 | M6: 19000 | N6: 810 | O6: 8000 | P6: 1800 | Q6: 0 | R6: 20000 | S6: 2500 | T6: 5000 | X6: 1500 | Y6: 4000 | AA6: 5000 | AC6: =SUM(B6:AB6) -> 152423.97 | AD6: =+AB6/2 -> 0 | AE6: 10000 | AF6: =AG6-AD6-AE6 -> 85000 | AG6: 95000 | AH6: =AC6/2-M6 -> 57211.985 | AI6: =AC6/2-D6 -> 60520.985 | AJ6: =AH6+AI6 -> 117732.97
A7: Setiembre | C7: 4369 | D7: 15706.32 | E7: 500 | F7: 27500 | H7: 3300 | I7: 3750 | J7: 1000 | K7: 23200 | L7: 7505 | M7: 23000 | N7: 810 | O7: 8000 | P7: 1800 | Q7: 2500 | R7: 19000 | S7: 2000 | T7: 5000 | U7: 13115 | V7: 1500 | W7: 3000 | X7: 800 | Y7: 2000 | AA7: 5000 | AC7: =SUM(B7:AB7) -> 174355.32 | AD7: =+AB7/2 -> 0 | AE7: 10000 | AF7: =AG7-AD7-AE7 -> 85000 | AG7: 95000 | AH7: =AC7/2-M7 -> 64177.66 | AI7: =AC7/2-D7 -> 71471.34 | AJ7: =AH7+AI7 -> 135649
A8: Octubre | B8: 27138.14 | D8: 15750 | E8: 0 | F8: 27500 | G8: 1100 | H8: 3300 | I8: 3000 | J8: 700 | K8: 26738 | L8: 18000 | M8: 16700 | N8: 810 | O8: 4400 | P8: 3600 | Q8: 2500 | R8: 20000 | S8: 2000 | T8: 5000 | W8: 3000 | X8: 800 | Y8: 2000 | AA8: 5000 | AC8: =SUM(B8:AB8) -> 189036.14 | AD8: =+AB8/2 -> 0 | AE8: 10000 | AF8: =AG8-AD8-AE8 -> 85000 | AG8: 95000 | AH8: =AC8/2-M8 -> 77818.07 | AI8: =AC8/2-D8 -> 78768.07 | AJ8: =AH8+AI8 -> 156586.14
A9: Noviembre | C9: 4369 | D9: 15800 | E9: 0 | F9: 27500 | G9: 1100 | H9: 3300 | I9: 3000 | J9: 700 | K9: 18000 | L9: 10000 | M9: 7500 | N9: 810 | O9: 4400 | P9: 3600 | Q9: 2500 | R9: 20000 | S9: 2000 | T9: 5000 | W9: 3000 | X9: 800 | Y9: 2000 | AA9: 5000 | AC9: =SUM(B9:AB9) -> 140379 | AD9: =+AB9/2 -> 0 | AE9: 10000 | AF9: =AG9-AD9-AE9 -> 85000 | AG9: 95000 | AH9: =AC9/2-M9 -> 62689.5 | AI9: =AC9/2-D9 -> 54389.5 | AJ9: =AH9+AI9 -> 117079
A10: Diciembre | D10: 15800 | E10: 0 | F10: 45000 | G10: 1100 | H10: 3300 | I10: 3000 | J10: 700 | K10: 18000 | L10: 10000 | M10: 7500 | N10: 810 | O10: 4400 | P10: 3600 | Q10: 2500 | R10: 20000 | S10: 2000 | T10: 5000 | W10: 3000 | X10: 800 | Y10: 2000 | AA10: 5000 | AC10: =SUM(B10:AB10) -> 153510 | AD10: =+AB10/2 -> 0 | AE10: 10000 | AF10: =AG10-AD10-AE10 -> 85000 | AG10: 95000 | AH10: =AC10/2-M10 -> 69255 | AI10: =AC10/2-D10 -> 60955 | AJ10: =AH10+AI10 -> 130210
A12: Real
A13: Mes | B13: Seguro | C13: Patente | D13: Contenedores | E13: Jardin | F13: Niñera | G13: SIET | H13: Internet | I13: Luz | J13: Gastos terreno | K13: Tarjeta CDE | L13: Tarjeta ITAU | M13: Tarjeta recompensa | N13: Amandaye | O13: Nafta y peaje | P13: Corte pasto | Q13: Perros | R13: Comida | S13: Limpieza | T13: paseo | U13: Camioneta | V13: Ablandador | W13: Jardineria | X13: Banco y seguro | Y13: Regalos | Z13: Gas y calefacción | AA13: Extra
A14: Mayo | B14: =IF(Mayo!B33>0,Mayo!B33,"") | C14: =IF(Mayo!C33>0,Mayo!C33,"") | D14: =IF(Mayo!D33>0,Mayo!D33,"") -> 15452.77 | E14: =IF(Mayo!E33>0,Mayo!E33,"") -> 10570 | F14: =IF(Mayo!F33>0,Mayo!F33,"") -> 26054 | G14: =IF(Mayo!G33>0,Mayo!G33,"") -> 980 | H14: =IF(Mayo!H33>0,Mayo!H33,"") -> 3291.56 | I14: =IF(Mayo!I33>0,Mayo!I33,"") -> 2144.26 | ... AA14: =IF(Mayo!AA33>0,Mayo!AA33,"") -> 4705.57
A15: Junio | B15: =IF(Junio!B32>0,Junio!B32,"") | C15: =IF(Junio!C32>0,Junio!C32,"") | D15: =IF(Junio!D32>0,Junio!D32,"") -> 15540.52 | E15: =IF(Junio!E32>0,Junio!E32,"") -> 10990.82 | F15: =IF(Junio!F32>0,Junio!F32,"") -> 37432 | G15: =IF(Junio!G32>0,Junio!G32,"") -> 1015 | H15: =IF(Junio!H32>0,Junio!H32,"") -> 3291.56 | I15: =IF(Junio!I32>0,Junio!I32,"") -> 2841.65 | ... Y15: =IF(Junio!Y32>0,Junio!Y32,"") -> 2432.95 | Z15: =IF(Junio!AA32>0,Junio!AA32,"") -> 5500 | AA15: =IF(Junio!AB32>0,Junio!AB32,"") -> 21845.24
A16: Julio | B16: =IF(Julio!B33>0,Julio!B33,"") | C16: =IF(Julio!C33>0,Julio!C33,"") -> 4369 | D16: =IF(Julio!D33>0,Julio!D33,"") -> 15600 | E16: =IF(Julio!E33>0,Julio!E33,"") | F16: =IF(Julio!F33>0,Julio!F33,"") -> 26100 | G16: =IF(Julio!G33>0,Julio!G33,"") -> 1000 | H16: =IF(Julio!H33>0,Julio!H33,"") -> 3500 | I16: =IF(Julio!I33>0,Julio!I33,"") -> 3000 | ... AA16: =IF(Julio!AA33>0,Julio!AA33,"") -> 5000
A17: Agosto | B17: =IF(Agosto!B33>0,Agosto!B33,"") | C17: =IF(Agosto!C33>0,Agosto!C33,"") | D17: =IF(Agosto!D33>0,Agosto!D33,"") -> 15691 | E17: =IF(Agosto!E33>0,Agosto!E33,"") | F17: =IF(Agosto!F33>0,Agosto!F33,"") -> 28611 | G17: =IF(Agosto!G33>0,Agosto!G33,"") -> 1185 | H17: =IF(Agosto!H33>0,Agosto!H33,"") -> 3291.56 | I17: =IF(Agosto!I33>0,Agosto!I33,"") -> 3335.41 | ... AA17: =IF(Agosto!AA33>0,Agosto!AA33,"") -> 6388.06
A18: Setiembre | B18: =IF(Setiembre!B32>0,Setiembre!B32,"") | C18: =IF(Setiembre!C32>0,Setiembre!C32,"") -> 4369 | D18: =IF(Setiembre!D32>0,Setiembre!D32,"") -> 15706.32 | E18: =IF(Setiembre!E32>0,Setiembre!E32,"") -> 498 | F18: =IF(Setiembre!F32>0,Setiembre!F32,"") -> 26792 | G18: =IF(Setiembre!G32>0,Setiembre!G32,"") | H18: =IF(Setiembre!H32>0,Setiembre!H32,"") -> 3291.56 | I18: =IF(Setiembre!I32>0,Setiembre!I32,"") -> 3687.55 | ... AA18: =IF(Setiembre!AA32>0,Setiembre!AA32,"") -> 2374.73
A19: Octubre | B19: =IF(Octubre!B33>0,Octubre!B33,"") -> 27138.14 | C19: =IF(Octubre!C33>0,Octubre!C33,"") | D19: =IF(Octubre!D33>0,Octubre!D33,"") -> 15751.26 | E19: =IF(Octubre!E33>0,Octubre!E33,"") | F19: =IF(Octubre!F33>0,Octubre!F33,"") -> 25901 | G19: =IF(Octubre!G33>0,Octubre!G33,"") -> 998.36 | H19: =IF(Octubre!H33>0,Octubre!H33,"") -> 3291.56 | I19: =IF(Octubre!I33>0,Octubre!I33,"") -> 3274.43 | ... AA19: =IF(Octubre!AA33>0,Octubre!AA33,"") -> 7220.91
A20: Noviembre | B20: =IF(Noviembre!B32>0,Noviembre!B32,"") | C20: =IF(Noviembre!C32>0,Noviembre!C32,"") | D20: =IF(Noviembre!D32>0,Noviembre!D32,"") | E20: =IF(Noviembre!E32>0,Noviembre!E32,"") | F20: =IF(Noviembre!F32>0,Noviembre!F32,"") | G20: =IF(Noviembre!G32>0,Noviembre!G32,"") | H20: =IF(Noviembre!H32>0,Noviembre!H32,"") | I20: =IF(Noviembre!I32>0,Noviembre!I32,"") | ... AA20: =IF(Noviembre!AA32>0,Noviembre!AA32,"")
A21: Diciembre | B21: =IF(Diciembre!B33>0,Diciembre!B33,"") | C21: =IF(Diciembre!C33>0,Diciembre!C33,"") | D21: =IF(Diciembre!D33>0,Diciembre!D33,"") | E21: =IF(Diciembre!E33>0,Diciembre!E33,"") | F21: =IF(Diciembre!F33>0,Diciembre!F33,"") | G21: =IF(Diciembre!G33>0,Diciembre!G33,"") | H21: =IF(Diciembre!H33>0,Diciembre!H33,"") | I21: =IF(Diciembre!I33>0,Diciembre!I33,"") | ... AA21: =IF(Diciembre!AA33>0,Diciembre!AA33,"")
A23: Diferencia
A24: Mes | B24: Seguro | C24: Patente | D24: Contenedores | E24: Jardin | F24: Niñera | G24: SIET | H24: Internet | I24: Luz | J24: Gastos terreno | K24: Tarjeta CDE | L24: Tarjeta ITAU | M24: Tarjeta recompensa | N24: Amandaye | O24: Nafta y peaje | P24: Corte pasto | Q24: Perros | R24: Comida | S24: Limpieza | T24: paseo | U24: Camioneta | V24: Ablandador | W24: Jardineria | X24: Banco y seguro | Y24: Regalos | Z24: Gas y calefacción | AA24: Extra | AC24: Total desvío mes
A25: Mayo | B25: =IF(ISNUMBER(Mayo!B33),B3-Mayo!B33,"") -> 0 | C25: =IF(ISNUMBER(Mayo!C33),C3-Mayo!C33,"") -> 0 | D25: =IF(ISNUMBER(Mayo!D33),D3-Mayo!D33,"") -> 47.23 | E25: =IF(ISNUMBER(Mayo!E33),E3-Mayo!E33,"") -> 30 | F25: =IF(ISNUMBER(Mayo!F33),F3-Mayo!F33,"") -> 46 | G25: =IF(ISNUMBER(Mayo!G33),G3-Mayo!G33,"") -> 20 | H25: =IF(ISNUMBER(Mayo!H33),H3-Mayo!H33,"") -> 208.44 | I25: =IF(ISNUMBER(Mayo!I33),I3-Mayo!I33,"") -> 855.74 | ... AA25: =IF(ISNUMBER(Mayo!AA33),AA3-Mayo!AA33,"") -> 294.43 | AC25: =SUMIF(B25:AA25,"<>"&"") -> 12166.97
A26: Junio | B26: =IF(ISNUMBER(Junio!B32),B4-Junio!B32,"") | C26: =IF(ISNUMBER(Junio!C32),C4-Junio!C32,"") | D26: =IF(ISNUMBER(Junio!D32),D4-Junio!D32,"") -> 9.48 | E26: =IF(ISNUMBER(Junio!E32),E4-Junio!E32,"") -> -390.82 | F26: =IF(ISNUMBER(Junio!F32),F4-Junio!F32,"") -> -1932 | G26: =IF(ISNUMBER(Junio!G32),G4-Junio!G32,"") -> -15 | H26: =IF(ISNUMBER(Junio!H32),H4-Junio!H32,"") -> 208.44 | I26: =IF(ISNUMBER(Junio!I32),I4-Junio!I32,"") -> 158.35 | ... Y26: =IF(ISNUMBER(Junio!Y32),Y4-Junio!Y32,"") -> -432.95 | Z26: =IF(ISNUMBER(Junio!AA32),Z4-Junio!AA32,"") -> -1650 | AA26: =IF(ISNUMBER(Junio!AB32),AA4-Junio!AB32,"") -> -16845.24 | AC26: =SUMIF(B26:AA26,"<>"&"") -> -22136.24
A27: Julio | B27: =IF(ISNUMBER(Julio!B33),B5-Julio!B33,"") | C27: =IF(ISNUMBER(Julio!C33),C5-Julio!C33,"") -> 0 | D27: =IF(ISNUMBER(Julio!D33),D5-Julio!D33,"") -> 0 | E27: =IF(ISNUMBER(Julio!E33),E5-Julio!E33,"") -> 0 | F27: =IF(ISNUMBER(Julio!F33),F5-Julio!F33,"") -> 0 | G27: =IF(ISNUMBER(Julio!G33),G5-Julio!G33,"") -> 0 | H27: =IF(ISNUMBER(Julio!H33),H5-Julio!H33,"") -> 0 | I27: =IF(ISNUMBER(Julio!I33),I5-Julio!I33,"") -> 0 | ... AA27: =IF(ISNUMBER(Julio!AA33),AA5-Julio!AA33,"") -> 0 | AC27: =SUMIF(B27:AA27,"<>"&"") -> 0
A28: Agosto | B28: =IF(ISNUMBER(Agosto!B33),B6-Agosto!B33,"") | C28: =IF(ISNUMBER(Agosto!C33),C6-Agosto!C33,"") | D28: =IF(ISNUMBER(Agosto!D33),D6-Agosto!D33,"") -> 0 | E28: =IF(ISNUMBER(Agosto!E33),E6-Agosto!E33,"") | F28: =IF(ISNUMBER(Agosto!F33),F6-Agosto!F33,"") -> 0 | G28: =IF(ISNUMBER(Agosto!G33),G6-Agosto!G33,"") -> 0 | H28: =IF(ISNUMBER(Agosto!H33),H6-Agosto!H33,"") -> 0 | I28: =IF(ISNUMBER(Agosto!I33),I6-Agosto!I33,"") -> 0 | ... AA28: =IF(ISNUMBER(Agosto!AA33),AA6-Agosto!AA33,"") -> -1388.06 | AC28: =SUMIF(B28:AA28,"<>"&"") -> -1515.67
A29: Setiembre | B29: =IF(ISNUMBER(Setiembre!B32),B8-Setiembre!B32,"") | C29: =IF(ISNUMBER(Setiembre!C32),C7-Setiembre!C32,"") -> 0 | D29: =IF(ISNUMBER(Setiembre!D32),D7-Setiembre!D32,"") -> 0 | E29: =IF(ISNUMBER(Setiembre!E32),E7-Setiembre!E32,"") -> 2 | F29: =IF(ISNUMBER(Setiembre!F32),F7-Setiembre!F32,"") -> 708 | G29: =IF(ISNUMBER(Setiembre!G32),G7-Setiembre!G32,"") | H29: =IF(ISNUMBER(Setiembre!H32),H7-Setiembre!H32,"") -> 8.44 | I29: =IF(ISNUMBER(Setiembre!I32),I7-Setiembre!I32,"") -> 62.45 | J29: =IF(ISNUMBER(Setiembre!J32),J7-Setiembre!J32,"") -> 0 | ... AA29: =IF(ISNUMBER(Setiembre!AA32),AA7-Setiembre!AA32,"") -> 2625.27 | AC29: =SUMIF(B29:AA29,"<>"&"") -> 3290.43
A30: Octubre | B30: =IF(ISNUMBER(Setiembre!B33),B9-Setiembre!B33,"") | C30: =IF(ISNUMBER(Octubre!C33),C8-Octubre!C33,"") -> 0 | D30: =IF(ISNUMBER(Octubre!D33),D8-Octubre!D33,"") -> -1.26 | E30: =IF(ISNUMBER(Octubre!E33),E8-Octubre!E33,"") -> 0 | F30: =IF(ISNUMBER(Octubre!F33),F8-Octubre!F33,"") -> 1599 | G30: =IF(ISNUMBER(Octubre!G33),G8-Octubre!G33,"") -> 101.64 | H30: =IF(ISNUMBER(Octubre!H33),H8-Octubre!H33,"") -> 8.44 | I30: =IF(ISNUMBER(Octubre!I33),I8-Octubre!I33,"") -> -274.43 | J30: =IF(ISNUMBER(Octubre!J33),J8-Octubre!J33,"") -> 0 | ... AA30: =IF(ISNUMBER(Octubre!AA33),AA8-Octubre!AA33,"") -> -2220.91 | AC30: =SUMIF(B30:AA30,"<>"&"") -> -5783.95
A31: Noviembre | B31: =IF(ISNUMBER(Noviembre!B32),B9-Noviembre!B32,"") | C31: =IF(ISNUMBER(Noviembre!C32),C9-Noviembre!C32,"") | D31: =IF(ISNUMBER(Noviembre!D32),D9-Noviembre!D32,"") | E31: =IF(ISNUMBER(Noviembre!E32),E9-Noviembre!E32,"") | F31: =IF(ISNUMBER(Noviembre!F32),F9-Noviembre!F32,"") | G31: =IF(ISNUMBER(Noviembre!G32),G9-Noviembre!G32,"") | H31: =IF(ISNUMBER(Noviembre!H32),H9-Noviembre!H32,"") | I31: =IF(ISNUMBER(Noviembre!I32),I9-Noviembre!I32,"") | ... AA31: =IF(ISNUMBER(Noviembre!AA32),AA9-Noviembre!AA32,"") | AC31: =SUMIF(B31:AA31,"<>"&"") -> 0
A32: Diciembre | B32: =IF(ISNUMBER(Diciembre!B33),B10-Diciembre!B33,"") | C32: =IF(ISNUMBER(Diciembre!C33),C10-Diciembre!C33,"") | D32: =IF(ISNUMBER(Diciembre!D33),D10-Diciembre!D33,"") | E32: =IF(ISNUMBER(Diciembre!E33),E10-Diciembre!E33,"") | F32: =IF(ISNUMBER(Diciembre!F33),F10-Diciembre!F33,"") | G32: =IF(ISNUMBER(Diciembre!G33),G10-Diciembre!G33,"") | H32: =IF(ISNUMBER(Diciembre!H33),H10-Diciembre!H33,"") | I32: =IF(ISNUMBER(Diciembre!I33),I10-Diciembre!I33,"") | ... AA32: =IF(ISNUMBER(Diciembre!AA33),AA10-Diciembre!AA33,"") | AC32: =SUMIF(B32:AA32,"<>"&"") -> 0
A33: Total desvío | B33: =SUMIF(B25:B32,"<>"&"") -> 0 | C33: =SUMIF(C25:C32,"<>"&"") -> 0 | D33: =SUMIF(D25:D32,"<>"&"") -> 55.45 | E33: =SUMIF(E25:E32,"<>"&"") -> -358.82 | F33: =SUMIF(F25:F32,"<>"&"") -> 421 | G33: =SUMIF(G25:G32,"<>"&"") -> 106.64 | H33: =SUMIF(H25:H32,"<>"&"") -> 433.76 | I33: =SUMIF(I25:I32,"<>"&"") -> 802.11 | ... AA33: =SUMIF(AA25:AA32,"<>"&"") -> -17534.51 | AC33: =SUMIF(B33:AA33,"<>"&"") -> -13978.46
A36: Fondo
B37: Objetivo | C37: Mayo | D37: Junio | E37: Julio | F37: Agosto | G37: Setiembre | H37: Octubre | I37: Noviembre | J37: Diciembre | L37: Total | M37: Sofi | N37: Nico
A38: Fondo | B38: 400000 | L38: =SUM(C38:J38) -> 0 | M38: =L38/2 -> 0 | N38: =L38/2 -> 0
A39: % completado | L39: =L38/B38 -> 0
A41: Gastos del fondo
A42: Fecha | B42: Descripción | C42: Monto
A53: Total gastos | C53: =SUM(C43:C52) -> 0
A54: Saldo neto | C54: =L38-C53 -> 0

Sheet Mayo
A1: Mes | B1: Seguro | C1: Patente | D1: Contenedores | E1: Jardin | F1: Niñera | G1: SIET | H1: Internet | I1: Luz | J1: Gastos terreno | K1: Tarjeta CDE | L1: Tarjeta ITAU | M1: Tarjeta recompensa | N1: Amandaye | O1: Nafta y peaje | P1: Corte pasto | Q1: Perros | R1: Comida | S1: Limpieza | T1: paseo | U1: Servicio camioneta | V1: Ablandador | W1: Jardineria | X1: Banco y seguros | Y1: Regalos | Z1: Gas y calefaccion | AA1: Extra | AB1: Cumple Roci | AC1: suma gastos | AD1: Observaciones
A2: 1 | AC2: =SUM(B2:AA2) -> 0
A3: 2 | AC3: =SUM(B3:AA3) -> 0
A4: 3 | R4: 2754.82 | AC4: =SUM(B4:AA4) -> 2754.82
A5: 4 | R5: 422.95 | X5: 68.64 | AC5: =SUM(B5:AA5) -> 491.59
A6: 5 | F6: 17944 | G6: 980 | AC6: =SUM(B6:AA6) -> 18924
A7: 6 | E7: 10570 | F7: 8110 | H7: =3327-35.44 -> 3291.56 | I7: =2180-35.74 -> 2144.26 | L7: =17828.45+253.56 -> 18082.01 | R7: 135 | X7: 334.65 | AA7: 2258.36 | AC7: =SUM(B7:AA7) -> 44925.84 | AD7: Uniforme Roci
A8: 7 | O8: 351 | R8: =454-8.26+506-8.3 -> 943.44 | T8: 1540 | X8: =2.27*40 -> 90.8 | AC8: =SUM(B8:AA8) -> 2925.24
A9: 8 | J9: 700 | N9: 810 | O9: =1000-16.39 -> 983.61 | R9: =452-2.93+179-4.85 -> 623.22 | T9: 500 | AA9: =899-14.74 -> 884.26 | AC9: =SUM(B9:AA9) -> 4501.09 | AD9: Botas Roci
A10: 9 | O10: 1321 | T10: =1037-17 -> 1020 | AC10: =SUM(B10:AA10) -> 2341
A11: 10 | O11: 3637 | R11: =205-3.5 -> 201.5 | T11: =205-3.5 -> 201.5 | AC11: =SUM(B11:AA11) -> 4040
A12: 11 | D12: 15452.77 | O12: -52.65 | R12: =709-15.08+920-6.49+396-1.39+347-11.65 -> 2337.39 | AC12: =SUM(B12:AA12) -> 17737.51
A13: 12 | O13: -545.55 | R13: =404.98-7.36 -> 397.62 | U13: =5900-96.72 -> 5803.28 | W13: =290-4.75 -> 285.25 | AC13: =SUM(B13:AA13) -> 5940.6 | AD13: 2 cubiertas chery
A14: 13 | Q14: =2490-40.82 -> 2449.18 | U14: =8725-143.03 -> 8581.97 | AC14: =SUM(B14:AA14) -> 11031.15
A15: 14 | AC15: =SUM(B15:AA15) -> 0
A16: 15 | R16: =450-7.38 -> 442.62 | X16: 215 | AC16: =SUM(B16:AA16) -> 657.62
A17: 16 | R17: =682-11.38+1322-21.67+113-1.85 -> 2082.1 | AC17: =SUM(B17:AA17) -> 2082.1
A18: 17 | AC18: =SUM(B18:AA18) -> 0
A19: 18 | R19: =380-6.23 -> 373.77 | AC19: =SUM(B19:AA19) -> 373.77
A20: 19 | R20: =106-1.74 -> 104.26 | AA20: =234+515-8.44-3.84 -> 736.72 | AC20: =SUM(B20:AA20) -> 840.98
A21: 20 | R21: =858+498-15.6-8.92+136-2.23 -> 1465.25 | AC21: =SUM(B21:AA21) -> 1465.25
A22: 21 | M22: 22127.68 | R22: =524+414-8.59-7.21 -> 922.2 | Z22: 500 | AC22: =SUM(B22:AA22) -> 23549.88 | AD22: retiro cajero
A23: 22 | R23: =932.73+320.86-16.96-5.83 -> 1230.8 | AC23: =SUM(B23:AA23) -> 1230.8
A24: 23 | O24: 3631 | AC24: =SUM(B24:AA24) -> 3631
A25: 24 | O25: -544.65 | R25: =862-12.46+474-7.77 -> 1315.77 | W25: =1000-16.39 -> 983.61 | AA25: =840-13.77 -> 826.23 | AC25: =SUM(B25:AA25) -> 2580.96 | AD25: China City
A26: 25 | R26: =606-13.14 -> 592.86 | S26: 150 | AC26: =SUM(B26:AA26) -> 742.86
A27: 26 | R27: =759-12.98 -> 746.02 | Y27: =1810-29.67 -> 1780.33 | AC27: =SUM(B27:AA27) -> 2526.35 | AD27: Pantalones Roci
A28: 27 | R28: =662-10.86 -> 651.14 | AC28: =SUM(B28:AA28) -> 651.14
A29: 28 | R29: =444-6.38+248-4.07 -> 681.55 | AC29: =SUM(B29:AA29) -> 681.55
A30: 29 | R30: =671.07-12.2+545-8.94 -> 1194.93 | AC30: =SUM(B30:AA30) -> 1194.93
A31: 30 | AC31: =SUM(B31:AA31) -> 0
A32: 31 | B32: 0 | C32: 0 | K32: 0 | P32: 0 | S32: 661 | V32: 0 | AC32: =SUM(B32:AA32) -> 661
A33: Total | B33: =IF(COUNTA(B2:B32)>0,SUM(B2:B32),"") -> 0 | C33: =IF(COUNTA(C2:C32)>0,SUM(C2:C32),"") -> 0 | D33: =IF(COUNTA(D2:D32)>0,SUM(D2:D32),"") -> 15452.77 | E33: =IF(COUNTA(E2:E32)>0,SUM(E2:E32),"") -> 10570 | F33: =IF(COUNTA(F2:F32)>0,SUM(F2:F32),"") -> 26054 | G33: =IF(COUNTA(G2:G32)>0,SUM(G2:G32),"") -> 980 | H33: =IF(COUNTA(H2:H32)>0,SUM(H2:H32),"") -> 3291.56 | I33: =IF(COUNTA(I2:I32)>0,SUM(I2:I32),"") -> 2144.26 | ... AC33: =IF(COUNTA(AC2:AC32)>0,SUM(AC2:AC32),"") -> 158483.03

Sheet Junio
A1: Mes | B1: Seguro | C1: Patente | D1: Contenedores | E1: Jardin | F1: Niñera | G1: SIET | H1: Internet | I1: Luz | J1: Gastos terreno | K1: Tarjeta CDE | L1: Tarjeta ITAU | M1: Tarjeta recompensa | N1: Amandaye | O1: Nafta y peaje | P1: Corte pasto | Q1: Perros | R1: Comida | S1: Limpieza | T1: paseo | U1: Servicio camioneta | V1: Ablandador | W1: Jardineria | X1: Banco y seguros | Y1: Regalos | Z1: Suscripciones | AA1: Gas y calefacción | AB1: Extra | AC1: Cumple Roci | AD1: suma gastos | AE1: Observaciones
A2: 1 | R2: =2604.85+606-9.93+408+237-0.84+423-6.93+504-8.26+1702-24.55 -> 6434.34 | AB2: =208-3.41 -> 204.59 | AD2: =SUM(B2:AB2) -> 6638.93 | AE2: Biogrip
A3: 2 | E3: 10990.82 | H3: =3327-35.44 -> 3291.56 | I3: =2889-47.35 -> 2841.65 | R3: =398-6.52 -> 391.48 | AD3: =SUM(B3:AB3) -> 17515.51
A4: 3 | R4: =640-11.03 -> 628.97 | AD4: =SUM(B4:AB4) -> 628.97
A5: 4 | R5: =405-7.18 -> 397.82 | AB5: =980+500+256-8.2-4.2 -> 1723.6 | AD5: =SUM(B5:AB5) -> 2121.42 | AE5: Vidrio, silicona, pistola silicona
A6: 5 | F6: 17944 | R6: =550+431-7.53+550+459-7.72-10-7.5 -> 1957.25 | AB6: =99-1.62 -> 97.38 | AD6: =SUM(B6:AB6) -> 19998.63 | AE6: luz spot
A7: 6 | AD7: =SUM(B7:AB7) -> 0
A8: 7 | R8: =670.25+634.43 -> 1304.68 | AD8: =SUM(B8:AB8) -> 1304.68
A9: 8 | K9: =1290.7-4.51 -> 1286.19 | AB9: 2900 | AD9: =SUM(B9:AB9) -> 4186.19 | AE9: caravanas
A10: 9 | L10: =14136.35-4704+258.54 -> 9690.89 | R10: =582-9.99 -> 572.01 | AB10: =7700+4290-70.33 -> 11919.67 | AD10: =SUM(B10:AB10) -> 22182.57 | AE10: materiales almohadones
A11: 10 | D11: 15540.52 | F11: 8110 | G11: 1015 | J11: 1000 | N11: 810 | P11: 1800 | R11: =560-9.86 -> 550.14 | S11: =281-4.61 -> 276.39 | AD11: =SUM(B11:AB11) -> 29102.05
A12: 11 | M12: 21668.69 | AC12: =990-16.23 -> 973.77 | AD12: =SUM(B12:AB12) -> 21668.69
A13: 12 | R13: =817.79+327-14.87-5.64+428-19.04 -> 1533.24 | AD13: =SUM(B13:AB13) -> 1533.24
A14: 13 | X14: 215 | Y14: =30-0.49 -> 29.51 | AC14: 500 | AD14: =SUM(B14:AB14) -> 244.51 | AE14: seña salon
A15: 14 | R15: =685-11.82 -> 673.18 | Y15: 690 | AC15: =1515-24+84+701-11.49 -> 2264.51 | AD15: =SUM(B15:AB15) -> 1363.18 | AE15: tortera y mac fiestas
A16: 15 | R16: =1917.73-7.02+388 -> 2298.71 | S16: =1135-33.19 -> 1101.81 | AD16: =SUM(B16:AB16) -> 3400.52
A17: 16 | R17: =351.7+897+270-5.77-14.71-4.43 -> 1493.79 | AA17: 5500 | AD17: =SUM(B17:AB17) -> 6993.79
A18: 17 | F18: 11378 | R18: =1006-16.49 -> 989.51 | AD18: =SUM(B18:AB18) -> 12367.51
A19: 18 | Y19: =965+66+711-15.82-1.08-11.66 -> 1713.44 | AB19: 5000 | AD19: =SUM(B19:AB19) -> 6713.44 | AE19: Almohadones
A20: 19 | AD20: =SUM(B20:AB20) -> 0
A21: 20 | O21: 1001 | AD21: =SUM(B21:AB21) -> 1001
A22: 21 | O22: -196.6 | AC22: =1780-29.18+462-8.26+394-6.46+815-13.36+983+370-6.07+1052+1264-21.22+909-14.9+2461-40.34+1500-24.59+1250 -> 13075.62 | AD22: =SUM(B22:AB22) -> -196.6
A23: 22 | AD23: =SUM(B23:AB23) -> 0
A24: 23 | AD24: =SUM(B24:AB24) -> 0
A25: 24 | R25: =1340.91-S25-22.9 -> 401.01 | S25: 917 | AC25: 509 | AD25: =SUM(B25:AB25) -> 1318.01
A26: 25 | AD26: =SUM(B26:AB26) -> 0
A27: 26 | AD27: =SUM(B27:AB27) -> 0
A28: 27 | AD28: =SUM(B28:AB28) -> 0
A29: 28 | AD29: =SUM(B29:AB29) -> 0
A30: 29 | AD30: =SUM(B30:AB30) -> 0
A31: 30 | AD31: =SUM(B31:AB31) -> 0
A32: Total | B32: =IF(COUNTA(B2:B31)>0,SUM(B2:B31),"") | C32: =IF(COUNTA(C2:C31)>0,SUM(C2:C31),"") | D32: =IF(COUNTA(D2:D31)>0,SUM(D2:D31),"") -> 15540.52 | E32: =IF(COUNTA(E2:E31)>0,SUM(E2:E31),"") -> 10990.82 | F32: =IF(COUNTA(F2:F31)>0,SUM(F2:F31),"") -> 37432 | G32: =IF(COUNTA(G2:G31)>0,SUM(G2:G31),"") -> 1015 | H32: =IF(COUNTA(H2:H31)>0,SUM(H2:H31),"") -> 3291.56 | I32: =IF(COUNTA(I2:I31)>0,SUM(I2:I31),"") -> 2841.65 | ... Z32: =IF(COUNTA(Z2:Z31)>0,SUM(Z2:Z31),"") | AA32: =SUM(AA2:AA31) -> 5500 | AB32: =IF(COUNTA(AB2:AB31)>0,SUM(AB2:AB31),"") -> 21845.24 | AC32: =IF(COUNTA(AC2:AC31)>0,SUM(AC2:AC31),"") -> 17322.9 | AD32: =IF(COUNTA(AD2:AD31)>0,SUM(AD2:AD31),"") -> 160086.24

Sheet Julio
A1: Mes | B1: Seguro | C1: Patente | D1: Contenedores | E1: Jardin | F1: Niñera | G1: SIET | H1: Internet | I1: Luz | J1: Gastos terreno | K1: Tarjeta CDE | L1: Tarjeta ITAU | M1: Tarjeta recompensa | N1: Amandaye | O1: Nafta y peaje | P1: Corte pasto | Q1: Perros | R1: Comida | S1: Limpieza | T1: paseo | U1: Servicio camioneta | V1: Ablandador | W1: Jardineria | X1: Banco y seguros | Y1: Regalos | Z1: Suscripciones | AA1: Extra | AB1: Cumple Roci | AC1: suma gastos | AD1: Observaciones
A2: 1 | AC2: =SUM(B2:AA2) -> 0
A3: 2 | AC3: =SUM(B3:AA3) -> 0
A4: 3 | AC4: =SUM(B4:AA4) -> 0
A5: 4 | AC5: =SUM(B5:AA5) -> 0
A6: 5 | AC6: =SUM(B6:AA6) -> 0
A7: 6 | AC7: =SUM(B7:AA7) -> 0
A8: 7 | AC8: =SUM(B8:AA8) -> 0
A9: 8 | AC9: =SUM(B9:AA9) -> 0
A10: 9 | AC10: =SUM(B10:AA10) -> 0
A11: 10 | AC11: =SUM(B11:AA11) -> 0
A12: 11 | AC12: =SUM(B12:AA12) -> 0
A13: 12 | AC13: =SUM(B13:AA13) -> 0
... A31: 30 | AC31: =SUM(B31:AA31) -> 0
A32: 31 | C32: 4369 | D32: 15600 | E32: 0 | F32: 26100 | G32: 1000 | H32: 3500 | I32: 3000 | J32: 1000 | K32: 17700 | L32: 7500 | M32: 7500 | N32: 850 | O32: 4400 | P32: 1800 | Q32: 2500 | R32: 20000 | S32: 2500 | T32: 5000 | V32: 1500 | W32: 3000 | X32: 1500 | Y32: 2000 | AA32: 5000 | AC32: =SUM(B32:AA32) -> 137319
A33: Total | B33: =IF(COUNTA(B2:B32)>0,SUM(B2:B32),"") | C33: =IF(COUNTA(C2:C32)>0,SUM(C2:C32),"") -> 4369 | D33: =IF(COUNTA(D2:D32)>0,SUM(D2:D32),"") -> 15600 | E33: =IF(COUNTA(E2:E32)>0,SUM(E2:E32),"") -> 0 | F33: =IF(COUNTA(F2:F32)>0,SUM(F2:F32),"") -> 26100 | G33: =IF(COUNTA(G2:G32)>0,SUM(G2:G32),"") -> 1000 | H33: =IF(COUNTA(H2:H32)>0,SUM(H2:H32),"") -> 3500 | I33: =IF(COUNTA(I2:I32)>0,SUM(I2:I32),"") -> 3000 | ... AC33: =IF(COUNTA(AC2:AC32)>0,SUM(AC2:AC32),"") -> 137319

Sheet Agosto
A1: Mes | B1: Seguro | C1: Patente | D1: Contenedores | E1: Jardin | F1: Niñera | G1: SIET | H1: Internet | I1: Luz | J1: Gastos terreno | K1: Tarjeta CDE | L1: Tarjeta ITAU | M1: Tarjeta recompensa | N1: Amandaye | O1: Nafta y peaje | P1: Corte pasto | Q1: Perros | R1: Comida | S1: Limpieza | T1: paseo | U1: Servicio camioneta | V1: Ablandador | W1: Jardineria | X1: Banco y seguros | Y1: Regalos | Z1: Suscripciones | AA1: Extra | AB1: Cumple Roci | AC1: suma gastos | AD1: Observaciones
A2: 1 | AC2: =SUM(B2:AA2) -> 0
A3: 2 | R3: =194-3.53 -> 190.47 | X3: =120.81+60.4 -> 181.21 | AC3: =SUM(B3:AA3) -> 371.68
A4: 3 | O4: =500-8.19 -> 491.81 | R4: =1047-17.83 -> 1029.17 | AC4: =SUM(B4:AA4) -> 1520.98
A5: 4 | R5: =637.58+338-11.38-5.54+694-11.59 -> 1641.07 | AA5: =894-14.66 -> 879.34 | AC5: =SUM(B5:AA5) -> 2520.41 | AD5: luces spot
A6: 5 | R6: =161-2.64 -> 158.36 | AC6: =SUM(B6:AA6) -> 158.36
A7: 6 | F7: 19744 | G7: 1185 | H7: =3327-35.44 -> 3291.56 | I7: =3391-55.59 -> 3335.41 | L7: =256.98+13740.58 -> 13997.56 | R7: =170-2.57 -> 167.43 | AA7: =353-3.33 -> 349.67 | AC7: =SUM(B7:AA7) -> 42070.63 | AD7: comepa
A8: 7 | AC8: =SUM(B8:AA8) -> 0
A9: 8 | R9: =275-4.51 -> 270.49 | T9: =303.5-4.98 -> 298.52 | AC9: =SUM(B9:AA9) -> 569.01
A10: 9 | R10: =442+715-7.35-11.72-4.76+523-9.18+267 -> 1913.99 | T10: =1107.87-18.16 -> 1089.71 | AC10: =SUM(B10:AA10) -> 3003.7
A11: 10 | D11: 15691 | F11: 8345 | K11: 17999.74 | M11: 19000 | O11: =500-8.19 -> 491.81 | R11: 303.5 | T11: 494 | AC11: =SUM(B11:AA11) -> 62325.05
A12: 11 | F12: 522 | O12: 3920 | AC12: =SUM(B12:AA12) -> 4442
A13: 12 | O13: -862.4 | AC13: =SUM(B13:AA13) -> -862.4
A14: 13 | J14: 700 | N14: 810 | P14: 1800 | R14: 650 | AC14: =SUM(B14:AA14) -> 3960
A15: 14 | R15: =945-15.49 -> 929.51 | X15: 215 | AC15: =SUM(B15:AA15) -> 1144.51
A16: 15 | R16: =858+235+873-15.74-63.3-3.85 -> 1883.11 | Y16: =760-12.46 -> 747.54 | AC16: =SUM(B16:AA16) -> 2630.65
A17: 16 | R17: =513-8.41 -> 504.59 | AA17: =485-7.95 -> 477.05 | AC17: =SUM(B17:AA17) -> 981.64 | AD17: resistencia calefon
A18: 17 | AA18: 1584 | AC18: =SUM(B18:AA18) -> 1584 | AD18: Cena Berni
A19: 18 | O19: =500-8.19 -> 491.81 | AA19: =352+470+353-8.54-5.6-3.33 -> 1157.53 | AC19: =SUM(B19:AA19) -> 1649.34 | AD19: 3 comepa
A20: 19 | O20: 3900 | R20: =1040.99-18.39 -> 1022.6 | S20: =874-15.88 -> 858.12 | AA20: =281-4.61 -> 276.39 | AC20: =SUM(B20:AA20) -> 6057.11 | AD20: envio zartenes
A21: 20 | O21: -858 | R21: =727-12.92 -> 714.08 | T21: =70+1080-0.66+269.46-19.88+570-9.34 -> 1959.58 | Y21: =450-7.38 -> 442.62 | AC21: =SUM(B21:AA21) -> 2258.28 | AD21: regalo lolo
A22: 21 | O22: 150 | R22: 800 | S22: 1600 | AA22: 1150 | AC22: =SUM(B22:AA22) -> 3700 | AD22: farmacia
A23: 22 | O23: 2600 | R23: 1500 | AC23: =SUM(B23:AA23) -> 4100
A24: 23 | R24: =310-5.08 -> 304.92 | AC24: =SUM(B24:AA24) -> 304.92
A25: 24 | AC25: =SUM(B25:AA25) -> 0
A26: 25 | AC26: =SUM(B26:AA26) -> 0
A27: 26 | R27: =1437.41+331+728-5.43-24.91-12.57 -> 2453.5 | AC27: =SUM(B27:AA27) -> 2453.5
A28: 27 | AA28: =117-1.92+399 -> 514.08 | AC28: =SUM(B28:AA28) -> 514.08 | AD28: disfraces roci
A29: 28 | AC29: =SUM(B29:AA29) -> 0
A30: 29 | AC30: =SUM(B30:AA30) -> 0
A31: 30 | O31: =1000-16.39 -> 983.61 | T31: =271+387-6.34+260 -> 911.66 | AC31: =SUM(B31:AA31) -> 1895.27
A32: 31 | O32: 2000 | T32: 758 | U32: 0 | V32: 0 | Y32: =1860-31.08 -> 1828.92 | AC32: =SUM(B32:AA32) -> 4586.92
A33: Total | B33: =IF(COUNTA(B2:B32)>0,SUM(B2:B32),"") | C33: =IF(COUNTA(C2:C32)>0,SUM(C2:C32),"") | D33: =IF(COUNTA(D2:D32)>0,SUM(D2:D32),"") -> 15691 | E33: =IF(COUNTA(E2:E32)>0,SUM(E2:E32),"") | F33: =IF(COUNTA(F2:F32)>0,SUM(F2:F32),"") -> 28611 | G33: =IF(COUNTA(G2:G32)>0,SUM(G2:G32),"") -> 1185 | H33: =IF(COUNTA(H2:H32)>0,SUM(H2:H32),"") -> 3291.56 | I33: =IF(COUNTA(I2:I32)>0,SUM(I2:I32),"") -> 3335.41 | ... AC33: =IF(COUNTA(AC2:AC32)>0,SUM(AC2:AC32),"") -> 153939.64

Sheet Setiembre
A1: Mes | B1: Seguro | C1: Patente | D1: Contenedores | E1: Jardin | F1: Niñera | G1: SIET | H1: Internet | I1: Luz | J1: Gastos terreno | K1: Tarjeta CDE | L1: Tarjeta ITAU | M1: Tarjeta recompensa | N1: Amandaye | O1: Nafta y peaje | P1: Corte pasto | Q1: Perros | R1: Comida | S1: Limpieza | T1: paseo | U1: Servicio camioneta | V1: Ablandador | W1: Jardineria | X1: Banco y seguros | Y1: Regalos | Z1: gas y calefacción | AA1: Extra | AB1: Cumple Roci | AC1: suma gastos | AD1: Observaciones
A2: 1 | R2: =859.68-13.39 -> 846.29 | AC2: =SUM(B2:AA2) -> 846.29
A3: 2 | E3: 498 | F3: 18447 | R3: =605-44.65 -> 560.35 | AC3: =SUM(B3:AA3) -> 19505.35
A4: 3 | F4: 8345 | H4: =3327-35.44 -> 3291.56 | I4: =3749-61.45 -> 3687.55 | P4: 1800 | R4: =378+1112.2+742-15.61-6.43 -> 2210.16 | AC4: =SUM(B4:AA4) -> 19334.27
A5: 4 | R5: =263-19.4+177+0.14-3.22 -> 417.52 | AA5: 42 | AC5: =SUM(B5:AA5) -> 459.52
A6: 5 | K6: 23112.77 | R6: =542-7.64+587-9.62 -> 1111.74 | AA6: 300 | AC6: =SUM(B6:AA6) -> 24524.51 | AD6: circo
A7: 6 | L7: =7245.67+256.67 -> 7502.34 | R7: =755-12.38 -> 742.62 | W7: =1980-32.46 -> 1947.54 | AA7: =320-5.45+1244.58 -> 1559.13 | AC7: =SUM(B7:AA7) -> 11751.63
A8: 7 | AC8: =SUM(B8:AA8) -> 0
A9: 8 | U9: =13329-218.51 -> 13110.49 | AC9: =SUM(B9:AA9) -> 13110.49
A10: 9 | R10: =263-4.57+952-16.36 -> 1194.07 | AC10: =SUM(B10:AA10) -> 1194.07
A11: 10 | D11: 15706.32 | R11: =746+720-12.65-53.11 -> 1400.24 | AC11: =SUM(B11:AA11) -> 17106.56
A12: 11 | C12: 4369 | J12: 1000 | N12: 810 | R12: =898-14.72+0.94+785.75-14.29 -> 1655.68 | AA12: 270 | AC12: =SUM(B12:AA12) -> 8104.68
A13: 12 | AC13: =SUM(B13:AA13) -> 0
A14: 13 | O14: =500-8.19 -> 491.81 | R14: =180-2.95+197-3.23+80-5.9+240+460+450-7.38+248-4.07+315-5.72 -> 2140.75 | AC14: =SUM(B14:AA14) -> 2632.56
A15: 14 | R15: =761-13.2 -> 747.8 | AA15: =128-2.1 -> 125.9 | AC15: =SUM(B15:AA15) -> 873.7
A16: 15 | X16: 215 | AC16: =SUM(B16:AA16) -> 215
A17: 16 | AC17: =SUM(B17:AA17) -> 0
A18: 17 | Q18: =2550-41.8 -> 2508.2 | S18: =926-14.75 -> 911.25 | AC18: =SUM(B18:AA18) -> 3419.45
A19: 18 | M19: =21570.71+1511.04 -> 23081.75 | R19: =469+432+1666-7.31-26.74-8.53 -> 2524.42 | AC19: =SUM(B19:AA19) -> 25606.17
A20: 19 | R20: =449+616-7.36-10.1 -> 1047.54 | AC20: =SUM(B20:AA20) -> 1047.54
A21: 20 | AC21: =SUM(B21:AA21) -> 0
A22: 21 | AC22: =SUM(B22:AA22) -> 0
A23: 22 | R23: =662-10.9+692-11.34 -> 1331.76 | AC23: =SUM(B23:AA23) -> 1331.76
A24: 23 | AC24: =SUM(B24:AA24) -> 0
A25: 24 | O25: 3724 | R25: =119.18+540-11.8-1.95-39.84+720 -> 1325.59 | AC25: =SUM(B25:AA25) -> 5049.59
A26: 25 | O26: -819.28 | P26: 1800 | R26: =444.94-7.49+481+1769.48-6.64-30.72 -> 2650.57 | T26: =480-7.87+739.55-12.57+1006.45-16.5 -> 2189.06 | W26: 1300 | AC26: =SUM(B26:AA26) -> 7120.35
A27: 26 | AC27: =SUM(B27:AA27) -> 0
A28: 27 | AC28: =SUM(B28:AA28) -> 0
A29: 28 | R29: =1143+488-10.37+633-18.74-8+400 -> 2626.89 | AC29: =SUM(B29:AA29) -> 2626.89
A30: 29 | S30: =265.01-2.12 -> 262.89 | AA30: =79-1.3 -> 77.7 | AC30: =SUM(B30:AA30) -> 340.59
A31: 30 | R31: =1004-14.15+381-6.93 -> 1363.92 | AC31: =SUM(B31:AA31) -> 1363.92
A32: Total | B32: =IF(COUNTA(B2:B31)>0,SUM(B2:B31),"") | C32: =IF(COUNTA(C2:C31)>0,SUM(C2:C31),"") -> 4369 | D32: =IF(COUNTA(D2:D31)>0,SUM(D2:D31),"") -> 15706.32 | E32: =IF(COUNTA(E2:E31)>0,SUM(E2:E31),"") -> 498 | F32: =IF(COUNTA(F2:F31)>0,SUM(F2:F31),"") -> 26792 | G32: =IF(COUNTA(G2:G31)>0,SUM(G2:G31),"") | H32: =IF(COUNTA(H2:H31)>0,SUM(H2:H31),"") -> 3291.56 | I32: =IF(COUNTA(I2:I31)>0,SUM(I2:I31),"") -> 3687.55 | ... AC32: =IF(COUNTA(AC2:AC31)>0,SUM(AC2:AC31),"") -> 167564.89

Sheet Octubre
A1: Mes | B1: Seguro | C1: Patente | D1: Contenedores | E1: Jardin | F1: Niñera | G1: SIET | H1: Internet | I1: Luz | J1: Gastos terreno | K1: Tarjeta CDE | L1: Tarjeta ITAU | M1: Tarjeta recompensa | N1: Amandaye | O1: Nafta y peaje | P1: Corte pasto | Q1: Perros | R1: Comida | S1: Limpieza | T1: paseo | U1: Servicio camioneta | V1: Ablandador | W1: Jardineria | X1: Banco y seguros | Y1: Regalos | Z1: Suscripciones | AA1: Extra | AB1: Cumple Roci | AC1: suma gastos | AD1: Observaciones
A2: 1 | C2: 0 | E2: 0 | R2: =1076-17.64 -> 1058.36 | U2: 0 | AC2: =SUM(B2:AA2) -> 1058.36
A3: 2 | R3: =1237-39.84+540-18.97 -> 1718.19 | AC3: =SUM(B3:AA3) -> 1718.19
A4: 3 | F4: 18447 | O4: =500-8.19 -> 491.81 | R4: =131-2.23 -> 128.77 | T4: =1300-21.31+260-4.26 -> 1534.43 | AC4: =SUM(B4:AA4) -> 20602.01
A5: 4 | R5: =962+1100-15.77-18.03+1436-17.52+131-2.23 -> 3575.45 | AC5: =SUM(B5:AA5) -> 3575.45
A6: 5 | AC6: =SUM(B6:AA6) -> 0
A7: 6 | H7: =3327-35.44 -> 3291.56 | I7: =3329-54.57 -> 3274.43 | K7: 26737.25 | R7: =266-4.36 -> 261.64 | AC7: =SUM(B7:AA7) -> 33564.88
A8: 7 | J8: 700 | N8: 810 | R8: =281.35-4.65 -> 276.7 | AC8: =SUM(B8:AA8) -> 1786.7
A9: 8 | B9: =76.49+18.15+21856+5187.5 -> 27138.14 | R9: =342-3.37 -> 338.63 | AA9: 2500 | AC9: =SUM(B9:AA9) -> 29976.77 | AD9: Arreglo porton y luz
A10: 9 | G10: =1015-16.64 -> 998.36 | L10: =9705.89+8284.14 -> 17990.03 | R10: =743-13.51 -> 729.49 | AA10: 500 | AC10: =SUM(B10:AA10) -> 20217.88 | AD10: llave
A11: 10 | R11: =1240-91.48 -> 1148.52 | S11: =108+461-1.97-6.31 -> 560.72 | AA11: =1640+440-7.21 -> 2072.79 | AC11: =SUM(B11:AA11) -> 3782.03 | AD11: libros roci y auriculares
A12: 11 | R12: =385-7.56 -> 377.44 | W12: 500 | AC12: =SUM(B12:AA12) -> 877.44
A13: 12 | AC13: =SUM(B13:AA13) -> 0
A14: 13 | AC14: =SUM(B14:AA14) -> 0
A15: 14 | D15: 15751.26 | F15: 7454 | P15: 1800 | R15: =280+673+382-11.03-6.26-4.59 -> 1313.12 | AC15: =SUM(B15:AA15) -> 26318.38
A16: 15 | X16: 232.5 | AC16: =SUM(B16:AA16) -> 232.5
A17: 16 | R17: =1056-77.9 -> 978.1 | AC17: =SUM(B17:AA17) -> 978.1
A18: 17 | R18: =2213.22-34.71+460-33.95 -> 2604.56 | T18: =1000-16.39 -> 983.61 | AC18: =SUM(B18:AA18) -> 3588.17
A19: 18 | R19: =316-5.18+790+1090.89-13.03-18.37 -> 2160.31 | T19: 340 | AC19: =SUM(B19:AA19) -> 2500.31
A20: 19 | O20: =500-8.19 -> 491.81 | S20: =530-8.69 -> 521.31 | T20: 500 | AC20: =SUM(B20:AA20) -> 1513.12
A21: 20 | AC21: =SUM(B21:AA21) -> 0
A22: 21 | M22: =15187.97+1505.49 -> 16693.46 | R22: =819-6.64-12.83-21.77-21.2+405+1328+1293+358 -> 4140.56 | AC22: =SUM(B22:AA22) -> 20834.02
A23: 22 | R23: =602.5+1172.02 -> 1774.52 | AC23: =SUM(B23:AA23) -> 1774.52
A24: 23 | O24: 3921 | AC24: =SUM(B24:AA24) -> 3921
A25: 24 | O25: -941.04 | R25: =67-1.1+206.89-3.39+1395-19.27 -> 1645.13 | T25: =1100+440+160-2.62 -> 1697.38 | AC25: =SUM(B25:AA25) -> 2401.47
A26: 25 | R26: =540-39.84 -> 500.16 | S26: 3000 | T26: 2200 | AA26: =409+340-7.44 -> 741.56 | AC26: =SUM(B26:AA26) -> 6441.72 | AD26: comepa
A27: 26 | R27: =451+821-13.45-8.04 -> 1250.51 | AA27: =485-7.95+945-15.49 -> 1406.56 | AC27: =SUM(B27:AA27) -> 2657.07 | AD27: luces y sellador baño
A28: 27 | AC28: =SUM(B28:AA28) -> 0
A29: 28 | AC29: =SUM(B29:AA29) -> 0
A30: 29 | AC30: =SUM(B30:AA30) -> 0
A31: 30 | AC31: =SUM(B31:AA31) -> 0
A32: 31 | AC32: =SUM(B32:AA32) -> 0
A33: Total | B33: =IF(COUNTA(B2:B32)>0,SUM(B2:B32),"") -> 27138.14 | C33: =IF(COUNTA(C2:C32)>0,SUM(C2:C32),"") -> 0 | D33: =IF(COUNTA(D2:D32)>0,SUM(D2:D32),"") -> 15751.26 | E33: =IF(COUNTA(E2:E32)>0,SUM(E2:E32),"") -> 0 | F33: =IF(COUNTA(F2:F32)>0,SUM(F2:F32),"") -> 25901 | G33: =IF(COUNTA(G2:G32)>0,SUM(G2:G32),"") -> 998.36 | H33: =IF(COUNTA(H2:H32)>0,SUM(H2:H32),"") -> 3291.56 | I33: =IF(COUNTA(I2:I32)>0,SUM(I2:I32),"") -> 3274.43 | ... AC33: =IF(COUNTA(AC2:AC32)>0,SUM(AC2:AC32),"") -> 190320.09

Sheet Noviembre
A1: Mes | B1: Seguro | C1: Patente | D1: Contenedores | E1: Jardin | F1: Niñera | G1: SIET | H1: Internet | I1: Luz | J1: Gastos terreno | K1: Tarjeta CDE | L1: Tarjeta ITAU | M1: Tarjeta recompensa | N1: Amandaye | O1: Nafta y peaje | P1: Corte pasto | Q1: Perros | R1: Comida | S1: Limpieza | T1: paseo | U1: Servicio camioneta | V1: Ablandador | W1: Jardineria | X1: Banco y seguros | Y1: Regalos | Z1: Suscripciones | AA1: Extra | AB1: Cumple Roci | AC1: suma gastos | AD1: Observaciones
A2: 1 | AC2: =SUM(B2:AA2) -> 0
A3: 2 | AC3: =SUM(B3:AA3) -> 0
A4: 3 | AC4: =SUM(B4:AA4) -> 0
A5: 4 | AC5: =SUM(B5:AA5) -> 0
A6: 5 | AC6: =SUM(B6:AA6) -> 0
A7: 6 | AC7: =SUM(B7:AA7) -> 0
A8: 7 | AC8: =SUM(B8:AA8) -> 0
A9: 8 | AC9: =SUM(B9:AA9) -> 0
A10: 9 | AC10: =SUM(B10:AA10) -> 0
A11: 10 | AC11: =SUM(B11:AA11) -> 0
A12: 11 | AC12: =SUM(B12:AA12) -> 0
A13: 12 | AC13: =SUM(B13:AA13) -> 0
... A31: 30 | AC31: =SUM(B31:AA31) -> 0
A32: Total | B32: =IF(COUNTA(B2:B31)>0,SUM(B2:B31),"") | C32: =IF(COUNTA(C2:C31)>0,SUM(C2:C31),"") | D32: =IF(COUNTA(D2:D31)>0,SUM(D2:D31),"") | E32: =IF(COUNTA(E2:E31)>0,SUM(E2:E31),"") | F32: =IF(COUNTA(F2:F31)>0,SUM(F2:F31),"") | G32: =IF(COUNTA(G2:G31)>0,SUM(G2:G31),"") | H32: =IF(COUNTA(H2:H31)>0,SUM(H2:H31),"") | I32: =IF(COUNTA(I2:I31)>0,SUM(I2:I31),"") | ... AC32: =IF(COUNTA(AC2:AC31)>0,SUM(AC2:AC31),"") -> 0

Sheet Diciembre
A1: Mes | B1: Seguro | C1: Patente | D1: Contenedores | E1: Jardin | F1: Niñera | G1: SIET | H1: Internet | I1: Luz | J1: Gastos terreno | K1: Tarjeta CDE | L1: Tarjeta ITAU | M1: Tarjeta recompensa | N1: Amandaye | O1: Nafta y peaje | P1: Corte pasto | Q1: Perros | R1: Comida | S1: Limpieza | T1: paseo | U1: Servicio camioneta | V1: Ablandador | W1: Jardineria | X1: Banco y seguros | Y1: Regalos | Z1: Suscripciones | AA1: Extra | AB1: Cumple Roci | AC1: suma gastos | AD1: Observaciones
A2: 1 | AC2: =SUM(B2:AA2) -> 0
A3: 2 | AC3: =SUM(B3:AA3) -> 0
A4: 3 | AC4: =SUM(B4:AA4) -> 0
A5: 4 | AC5: =SUM(B5:AA5) -> 0
A6: 5 | AC6: =SUM(B6:AA6) -> 0
A7: 6 | AC7: =SUM(B7:AA7) -> 0
A8: 7 | AC8: =SUM(B8:AA8) -> 0
A9: 8 | AC9: =SUM(B9:AA9) -> 0
A10: 9 | AC10: =SUM(B10:AA10) -> 0
A11: 10 | AC11: =SUM(B11:AA11) -> 0
A12: 11 | AC12: =SUM(B12:AA12) -> 0
A13: 12 | AC13: =SUM(B13:AA13) -> 0
... A32: 31 | AC32: =SUM(B32:AA32) -> 0
A33: Total | B33: =IF(COUNTA(B2:B32)>0,SUM(B2:B32),"") | C33: =IF(COUNTA(C2:C32)>0,SUM(C2:C32),"") | D33: =IF(COUNTA(D2:D32)>0,SUM(D2:D32),"") | E33: =IF(COUNTA(E2:E32)>0,SUM(E2:E32),"") | F33: =IF(COUNTA(F2:F32)>0,SUM(F2:F32),"") | G33: =IF(COUNTA(G2:G32)>0,SUM(G2:G32),"") | H33: =IF(COUNTA(H2:H32)>0,SUM(H2:H32),"") | I33: =IF(COUNTA(I2:I32)>0,SUM(I2:I32),"") | ... AC33: =IF(COUNTA(AC2:AC32)>0,SUM(AC2:AC32),"") -> 0
